buencolors/__init__.py
buencolors/_version.py
buencolors/helpers.py
buencolors/palettes.py
buencolors/single_cell.py
buencolors/styles/pretty-plot.mplstyle
buencolors-1.0.0.dist-info/licenses/LICENSE
buencolors-1.0.0.dist-info/METADATA
buencolors-1.0.0.dist-info/WHEEL
buencolors-1.0.0.dist-info/top_level.txt
buencolors-1.0.0.dist-info/RECORD
