Metadata-Version: 2.4
Name: buencolors
Version: 1.0.0
Summary: A pythonic port of the BuenColors R library for handy color palettes.
Author-email: Austin Varela <aav4003@med.cornell.edu>, Caleb Lareau <lareauc@mskcc.org>
Maintainer-email: Austin Varela <aav4003@med.cornell.edu>
License-Expression: MIT
Project-URL: Homepage, https://github.com/austinv11/PyBuenColors
Project-URL: Repository, https://github.com/austinv11/PyBuenColors
Project-URL: Documentation, https://austinv11.github.io/PyBuenColors/
Project-URL: Bug Tracker, https://github.com/austinv11/PyBuenColors/issues
Project-URL: Changelog, https://github.com/austinv11/PyBuenColors/releases
Keywords: colors,visualization,matplotlib,data-science,palettes,bioinformatics
Classifier: Development Status :: 5 - Production/Stable
Classifier: Intended Audience :: Developers
Classifier: Intended Audience :: Science/Research
Classifier: Operating System :: OS Independent
Classifier: Programming Language :: Python :: 3
Classifier: Programming Language :: Python :: 3.11
Classifier: Programming Language :: Python :: 3.12
Classifier: Programming Language :: Python :: 3.13
Classifier: Programming Language :: Python :: 3.14
Classifier: Topic :: Scientific/Engineering :: Visualization
Classifier: Topic :: Software Development :: Libraries :: Python Modules
Classifier: Framework :: Matplotlib
Requires-Python: >=3.11
License-File: LICENSE
Requires-Dist: matplotlib>=3.9.0
Requires-Dist: numpy>=2.0.1
Requires-Dist: pandas>=2.3.0
Requires-Dist: scipy>=1.14.0
Provides-Extra: dev
Requires-Dist: setuptools>=80; extra == "dev"
Requires-Dist: mkdocs-material>=9.6.18; extra == "dev"
Requires-Dist: mkdocs>=1.6.1; extra == "dev"
Requires-Dist: pytest>=8.4.1; extra == "dev"
Requires-Dist: mkdocstrings[python]>=0.25; extra == "dev"
Requires-Dist: mkdocstrings-python>=1.0; extra == "dev"
Requires-Dist: mkdocs-jupyter>=0.25.1; extra == "dev"
Requires-Dist: mkdocs-api-autonav>=0.4.0; extra == "dev"
Requires-Dist: mkdocs-git-revision-date-localized-plugin>=1.5.0; extra == "dev"
Dynamic: license-file
